TINTOlib/__init__.py
TINTOlib/abstractImageMethod.py
TINTOlib/barGraph.py
TINTOlib/base.py
TINTOlib/bie.py
TINTOlib/combination.py
TINTOlib/distanceMatrix.py
TINTOlib/featureWrap.py
TINTOlib/igtd.py
TINTOlib/refined.py
TINTOlib/supertml.py
TINTOlib/tinto.py
TINTOlib/utils/Toolbox.py
TINTOlib/utils/config.py
TINTOlib/utils/mpiHill_UF.py
TINTOlib/utils/paraHill.py
tintolib-1.0.6.1.dist-info/METADATA
tintolib-1.0.6.1.dist-info/WHEEL
tintolib-1.0.6.1.dist-info/licenses/LICENSE
tintolib-1.0.6.1.dist-info/RECORD
