Metadata-Version: 2.4
Name: TINTOlib
Version: 1.0.6.1
Summary: Converting tabular data into images
Project-URL: Homepage, https://github.com/oeg-upm/TINTOlib-Documentation
Author-email: BorjaRei <borjareinoso@gmail.com>, manwestc <jcastillo@fi.upm.es>, DavidGonzalezFernandez <david.g.f.2@gmail.com>, JiayunLiu <jiayun.liu@upm.es>
License:                                  Apache License
License-File: LICENSE
Classifier: License :: OSI Approved :: Apache Software License
Classifier: Operating System :: OS Independent
Classifier: Programming Language :: Python :: 3
Requires-Python: >=3.8
Requires-Dist: bitstring==4.3.0
Requires-Dist: matplotlib==3.9.4
Requires-Dist: mpi4py==4.0.3
Requires-Dist: numpy==2.0.2
Requires-Dist: opencv-python==4.11.0.86
Requires-Dist: pandas==2.2.3
Requires-Dist: scikit-learn==1.6.1
